eckity/__init__.py
eckity/before_after_publisher.py
eckity/event_based_operator.py
eckity/individual.py
eckity/population.py
eckity/subpopulation.py
eckity/algorithms/__init__.py
eckity/algorithms/algorithm.py
eckity/algorithms/simple_evolution.py
eckity/algorithms/tests/__init__.py
eckity/algorithms/tests/test_simple_evolution.py
eckity/base/__init__.py
eckity/base/typed_functions.py
eckity/base/types.py
eckity/base/untyped_functions.py
eckity/base/utils.py
eckity/breeders/__init__.py
eckity/breeders/breeder.py
eckity/breeders/simple_breeder.py
eckity/breeders/tests/__init__.py
eckity/breeders/tests/test_simple_breeder.py
eckity/creators/__init__.py
eckity/creators/creator.py
eckity/creators/ga_creators/__init__.py
eckity/creators/ga_creators/bit_string_vector_creator.py
eckity/creators/ga_creators/float_vector_creator.py
eckity/creators/ga_creators/int_vector_creator.py
eckity/creators/ga_creators/simple_vector_creator.py
eckity/creators/gp_creators/__init__.py
eckity/creators/gp_creators/full.py
eckity/creators/gp_creators/grow.py
eckity/creators/gp_creators/half.py
eckity/creators/gp_creators/tree_creator.py
eckity/creators/gp_creators/tests/__init__.py
eckity/creators/gp_creators/tests/test_full.py
eckity/creators/gp_creators/tests/test_grow.py
eckity/creators/gp_creators/tests/test_half.py
eckity/evaluators/__init__.py
eckity/evaluators/individual_evaluator.py
eckity/evaluators/population_evaluator.py
eckity/evaluators/simple_individual_evaluator.py
eckity/evaluators/simple_population_evaluator.py
eckity/fitness/__init__.py
eckity/fitness/fitness.py
eckity/fitness/gp_fitness.py
eckity/fitness/simple_fitness.py
eckity/genetic_encodings/__init__.py
eckity/genetic_encodings/ga/__init__.py
eckity/genetic_encodings/ga/bit_string_vector.py
eckity/genetic_encodings/ga/float_vector.py
eckity/genetic_encodings/ga/int_vector.py
eckity/genetic_encodings/ga/vector_individual.py
eckity/genetic_encodings/ga/tests/__init__.py
eckity-0.4.1.dist-info/licenses/LICENSE
eckity-0.4.1.dist-info/METADATA
eckity-0.4.1.dist-info/WHEEL
eckity-0.4.1.dist-info/top_level.txt
eckity-0.4.1.dist-info/RECORD
