Metadata-Version: 2.4
Name: eckity
Version: 0.4.1
Summary: EC-KitY: Evolutionary Computation Tool Kit in Python.
Home-page: https://www.eckity.org
Author: Moshe Sipper, Achiya Elyasaf, Itai Tzruia, Tomer Halperin
Author-email: sipper@gmail.com, achiya@bgu.ac.il, itaitz@post.bgu.ac.il, tomerhal@post.bgu.ac.il
License: GNU GPLv3
Project-URL: Bug Tracker, https://github.com/EC-KitY/EC-KitY/issues
License-File: LICENSE
Requires-Dist: numpy>=1.24.0
Requires-Dist: overrides>=7.0.0
Requires-Dist: pandas>=0.25.2
Dynamic: author
Dynamic: author-email
Dynamic: description
Dynamic: description-content-type
Dynamic: home-page
Dynamic: license
Dynamic: license-file
Dynamic: project-url
Dynamic: requires-dist
Dynamic: summary
